{ "compressionlevel":-1,
 "height":10,
 "infinite":false,
 "layers":[
        {
         "data":[8, 9, 10, 8, 8, 9, 10, 8, 8, 8, 8, 9, 8, 9, 9, 9, 9, 9, 9, 8, 9, 10, 8, 8, 8, 8, 9, 8, 9, 10,
            8, 8, 8, 8, 8, 9, 8, 8, 9, 8, 9, 8, 8, 9, 8, 9, 28, 8, 9, 8, 9, 8, 8, 8, 8, 8, 9, 8, 9, 9,
            8, 9, 8, 9, 8, 8, 8, 9, 8, 9, 10, 8, 9, 10, 28, 117, 117, 8, 9, 8, 9, 8, 8, 8, 10, 8, 9, 8, 9, 9,
            8, 9, 8, 9, 9, 8, 8, 10, 10, 9, 8, 8, 9, 117, 117, 117, 117, 117, 117, 117, 117, 117, 117, 9, 10, 8, 9, 9, 8, 9,
            8, 9, 8, 27, 10, 10, 9, 27, 10, 10, 8, 9, 10, 117, 9, 10, 117, 117, 10, 9, 8, 9, 8, 46, 10, 10, 10, 10, 8, 9,
            8, 9, 8, 9, 10, 8, 9, 10, 8, 9, 27, 10, 10, 8, 10, 10, 8, 9, 44, 9, 8, 9, 8, 9, 10, 8, 27, 10, 9, 9,
            8, 9, 8, 9, 10, 10, 26, 10, 8, 9, 8, 10, 10, 8, 10, 9, 10, 9, 8, 9, 8, 9, 8, 9, 10, 10, 8, 10, 9, 9,
            8, 9, 8, 9, 10, 9, 9, 8, 8, 8, 8, 27, 10, 8, 9, 10, 134, 135, 8, 9, 46, 10, 8, 8, 9, 10, 8, 44, 9, 9,
            8, 9, 8, 9, 10, 8, 9, 8, 9, 8, 8, 9, 10, 8, 9, 9, 152, 153, 9, 9, 9, 9, 10, 8, 9, 10, 8, 8, 9, 9,
            8, 8, 8, 8, 9, 8, 8, 8, 9, 8, 8, 9, 10, 8, 9, 22, 22, 22, 22, 22, 9, 9, 10, 8, 9, 10, 8, 8, 8, 9],
         "height":10,
         "id":1,
         "name":"floor",
         "opacity":1,
         "type":"tilelayer",
         "visible":true,
         "width":30,
         "x":0,
         "y":0
        }, 
        {
         "data":[22, 22, 22, 22, 22, 22, 22, 22, 22, 22, 22, 22, 22, 22, 23, 0, 21, 22, 22, 22, 22, 22, 22, 22, 22, 22, 22, 22, 22, 22,
            22, 22, 22, 22, 22, 22, 22, 22, 22, 22, 22, 22, 22, 22, 23, 0, 21, 22, 22, 22, 22, 22, 22, 22, 22, 22, 22, 22, 22, 22,
            1, 59, 59, 78, 59, 59, 59, 59, 59, 59, 58, 57, 40, 40, 41, 9, 39, 40, 40, 59, 74, 58, 78, 60, 93, 94, 59, 40, 77, 2,
            23, 0, 0, 0, 0, 0, 0, 9, 117, 117, 117, 0, 0, 0, 9, 9, 9, 9, 9, 0, 0, 0, 0, 0, 0, 0, 9, 0, 0, 21,
            23, 0, 0, 0, 0, 0, 0, 0, 0, 0, 0, 0, 0, 0, 0, 0, 0, 0, 0, 0, 0, 0, 0, 0, 0, 0, 0, 0, 0, 21,
            23, 0, 0, 0, 0, 0, 0, 0, 0, 0, 0, 0, 0, 0, 0, 0, 0, 0, 0, 0, 0, 0, 0, 0, 0, 0, 0, 0, 0, 21,
            23, 0, 0, 0, 0, 0, 0, 0, 0, 0, 0, 0, 0, 0, 0, 0, 0, 0, 0, 0, 0, 0, 0, 0, 0, 0, 0, 0, 0, 21,
            19, 4, 4, 4, 4, 4, 4, 4, 4, 4, 4, 4, 4, 4, 4, 4, 5, 3, 4, 4, 4, 4, 4, 4, 4, 4, 4, 4, 4, 20,
            22, 22, 22, 22, 22, 22, 22, 22, 22, 22, 22, 22, 22, 22, 22, 22, 23, 21, 22, 22, 22, 22, 22, 22, 22, 22, 22, 22, 22, 22,
            40, 149, 40, 40, 40, 79, 40, 40, 40, 40, 40, 40, 149, 40, 40, 40, 41, 39, 40, 40, 40, 127, 128, 40, 78, 40, 40, 40, 149, 40],
         "height":10,
         "id":2,
         "name":"wall",
         "opacity":1,
         "type":"tilelayer",
         "visible":true,
         "width":30,
         "x":0,
         "y":0
        }, 
        {
         "data":[0, 0, 0, 0, 0, 0, 0, 0, 0, 0, 0, 0, 0, 0, 245, 246, 247, 0, 0, 0, 0, 0, 0, 0, 0, 0, 0, 0, 0, 0,
            0, 0, 0, 0, 0, 0, 0, 0, 0, 0, 0, 0, 0, 0, 245, 246, 247, 0, 0, 0, 0, 0, 0, 0, 0, 0, 0, 0, 0, 0,
            0, 0, 0, 0, 0, 0, 0, 0, 0, 0, 0, 0, 0, 0, 263, 264, 265, 0, 97, 0, 0, 0, 0, 0, 0, 0, 0, 0, 0, 0,
            0, 0, 0, 0, 0, 0, 0, 0, 0, 0, 0, 0, 0, 0, 0, 0, 0, 0, 115, 0, 0, 0, 0, 0, 0, 0, 0, 0, 0, 0,
            0, 0, 0, 0, 0, 0, 0, 0, 0, 0, 0, 0, 0, 0, 0, 0, 0, 0, 0, 0, 0, 0, 0, 0, 0, 0, 0, 0, 0, 0,
            0, 0, 0, 0, 0, 0, 0, 0, 0, 0, 0, 0, 0, 0, 0, 0, 0, 0, 0, 0, 0, 0, 0, 0, 0, 0, 0, 0, 0, 0,
            0, 0, 0, 0, 0, 0, 0, 0, 0, 0, 0, 0, 0, 0, 0, 0, 0, 0, 0, 0, 0, 0, 0, 0, 0, 0, 0, 0, 0, 0,
            0, 0, 0, 0, 0, 0, 0, 0, 0, 0, 0, 0, 0, 0, 0, 0, 0, 0, 0, 0, 0, 0, 0, 0, 0, 0, 0, 0, 0, 0,
            0, 0, 0, 0, 0, 0, 0, 0, 0, 0, 0, 0, 0, 0, 0, 0, 0, 0, 0, 0, 0, 0, 0, 0, 0, 0, 0, 0, 0, 0,
            0, 0, 0, 0, 0, 0, 0, 0, 0, 0, 0, 0, 0, 0, 0, 0, 0, 0, 0, 0, 0, 0, 0, 0, 0, 0, 0, 0, 0, 0],
         "height":10,
         "id":3,
         "name":"decor1",
         "opacity":1,
         "type":"tilelayer",
         "visible":true,
         "width":30,
         "x":0,
         "y":0
        }, 
        {
         "data":[0, 0, 0, 0, 0, 0, 0, 0, 0, 0, 0, 0, 0, 0, 0, 0, 0, 0, 0, 0, 0, 0, 0, 0, 0, 0, 0, 0, 0, 0,
            0, 0, 0, 0, 0, 0, 0, 37, 0, 0, 0, 0, 0, 0, 0, 0, 0, 0, 0, 0, 0, 37, 0, 0, 0, 0, 0, 0, 0, 0,
            0, 220, 0, 0, 0, 0, 0, 55, 0, 0, 220, 0, 0, 0, 0, 0, 0, 0, 0, 0, 0, 55, 0, 0, 0, 0, 0, 127, 128, 220,
            0, 0, 0, 0, 0, 0, 0, 73, 0, 0, 0, 0, 0, 0, 0, 0, 0, 0, 0, 0, 0, 73, 0, 0, 0, 0, 0, 145, 146, 0,
            0, 0, 0, 0, 0, 0, 0, 0, 0, 0, 0, 0, 0, 0, 0, 0, 0, 0, 0, 0, 0, 0, 0, 0, 0, 0, 0, 0, 0, 0,
            0, 0, 0, 0, 0, 0, 0, 0, 0, 0, 0, 0, 0, 0, 0, 0, 0, 0, 0, 0, 0, 0, 0, 0, 0, 0, 0, 0, 0, 0,
            0, 0, 0, 0, 0, 0, 0, 0, 0, 0, 0, 0, 0, 0, 0, 0, 0, 0, 0, 0, 0, 0, 0, 0, 0, 0, 0, 0, 0, 0,
            0, 0, 0, 0, 0, 0, 0, 0, 0, 0, 0, 0, 0, 0, 0, 0, 0, 0, 0, 0, 0, 0, 0, 0, 0, 0, 0, 0, 0, 0,
            0, 0, 0, 0, 0, 0, 0, 0, 0, 0, 0, 0, 0, 0, 0, 0, 0, 0, 0, 0, 0, 0, 0, 0, 0, 0, 0, 0, 0, 0,
            0, 0, 0, 0, 0, 0, 0, 0, 0, 0, 0, 0, 0, 0, 0, 0, 113, 114, 0, 0, 0, 0, 0, 0, 0, 0, 0, 0, 0, 0],
         "height":10,
         "id":4,
         "locked":true,
         "name":"decor2",
         "opacity":1,
         "type":"tilelayer",
         "visible":true,
         "width":30,
         "x":0,
         "y":0
        }, 
        {
         "draworder":"topdown",
         "id":5,
         "name":"object",
         "objects":[
                {
                 "height":0,
                 "id":1,
                 "name":"chordStart",
                 "point":true,
                 "rotation":0,
                 "type":"chord",
                 "visible":true,
                 "width":0,
                 "x":16,
                 "y":138
                }, 
                {
                 "height":0,
                 "id":2,
                 "name":"playerStart",
                 "point":true,
                 "rotation":0,
                 "type":"",
                 "visible":true,
                 "width":0,
                 "x":16,
                 "y":197
                }, 
                {
                 "height":0,
                 "id":5,
                 "name":"chordBattle",
                 "point":true,
                 "rotation":0,
                 "type":"chord",
                 "visible":true,
                 "width":0,
                 "x":565.86,
                 "y":238.826
                }, 
                {
                 "height":0,
                 "id":7,
                 "name":"milestone",
                 "point":true,
                 "rotation":0,
                 "type":"",
                 "visible":true,
                 "width":0,
                 "x":895.599,
                 "y":121.361
                }, 
                {
                 "height":0,
                 "id":9,
                 "name":"chordEnd",
                 "point":true,
                 "rotation":0,
                 "type":"chord",
                 "visible":true,
                 "width":0,
                 "x":931.416,
                 "y":120.542
                }, 
                {
                 "height":0,
                 "id":10,
                 "name":"spider",
                 "point":true,
                 "rotation":0,
                 "type":"monster",
                 "visible":true,
                 "width":0,
                 "x":209,
                 "y":151
                }, 
                {
                 "height":0,
                 "id":11,
                 "name":"spider",
                 "point":true,
                 "rotation":0,
                 "type":"monster",
                 "visible":true,
                 "width":0,
                 "x":411,
                 "y":220
                }, 
                {
                 "height":0,
                 "id":12,
                 "name":"spider",
                 "point":true,
                 "rotation":0,
                 "type":"monster",
                 "visible":true,
                 "width":0,
                 "x":726,
                 "y":154
                }, 
                {
                 "height":0,
                 "id":13,
                 "name":"fly",
                 "point":true,
                 "rotation":0,
                 "type":"monster",
                 "visible":true,
                 "width":0,
                 "x":478,
                 "y":198
                }, 
                {
                 "height":0,
                 "id":14,
                 "name":"fly",
                 "point":true,
                 "rotation":0,
                 "type":"monster",
                 "visible":true,
                 "width":0,
                 "x":663,
                 "y":216
                }, 
                {
                 "height":0,
                 "id":15,
                 "name":"fly",
                 "point":true,
                 "rotation":0,
                 "type":"monster",
                 "visible":true,
                 "width":0,
                 "x":258,
                 "y":218
                }],
         "opacity":1,
         "type":"objectgroup",
         "visible":true,
         "x":0,
         "y":0
        }],
 "nextlayerid":6,
 "nextobjectid":16,
 "orientation":"orthogonal",
 "renderorder":"right-down",
 "tiledversion":"1.11.0",
 "tileheight":32,
 "tilesets":[
        {
         "columns":18,
         "firstgid":1,
         "image":"..\/Royal Dungeon Tileset.png",
         "imageheight":704,
         "imagewidth":576,
         "margin":0,
         "name":"Royal Dungeon Tileset",
         "spacing":0,
         "tilecount":396,
         "tileheight":32,
         "tiles":[
                {
                 "id":10,
                 "properties":[
                        {
                         "name":"collides",
                         "type":"bool",
                         "value":true
                        }]
                }, 
                {
                 "id":11,
                 "properties":[
                        {
                         "name":"collides",
                         "type":"bool",
                         "value":true
                        }]
                }, 
                {
                 "id":12,
                 "properties":[
                        {
                         "name":"collides",
                         "type":"bool",
                         "value":true
                        }]
                }, 
                {
                 "id":21,
                 "properties":[
                        {
                         "name":"collides",
                         "type":"bool",
                         "value":true
                        }]
                }, 
                {
                 "id":49,
                 "properties":[
                        {
                         "name":"collides",
                         "type":"bool",
                         "value":true
                        }]
                }, 
                {
                 "id":151,
                 "properties":[
                        {
                         "name":"collides",
                         "type":"bool",
                         "value":true
                        }]
                }, 
                {
                 "id":152,
                 "properties":[
                        {
                         "name":"collides",
                         "type":"bool",
                         "value":true
                        }]
                }],
         "tilewidth":32
        }],
 "tilewidth":32,
 "type":"map",
 "version":"1.10",
 "width":30
}